git_mcp/__init__.py
git_mcp/cli.py
git_mcp/mcp_server.py
git_mcp/claude_commands/README.md
git_mcp/claude_commands/__init__.py
git_mcp/claude_commands/doc.md
git_mcp/claude_commands/implement.md
git_mcp/claude_commands/issue.md
git_mcp/claude_commands/plan.md
git_mcp/claude_commands/pr.md
git_mcp/claude_commands/test.md
git_mcp/codex_commands/README.md
git_mcp/codex_commands/__init__.py
git_mcp/codex_commands/doc.md
git_mcp/codex_commands/implement.md
git_mcp/codex_commands/issue.md
git_mcp/codex_commands/plan.md
git_mcp/codex_commands/pr.md
git_mcp/codex_commands/test.md
git_mcp/commands/__init__.py
git_mcp/commands/issue.py
git_mcp/commands/mr.py
git_mcp/commands/project.py
git_mcp/core/__init__.py
git_mcp/core/config.py
git_mcp/core/exceptions.py
git_mcp/core/logging.py
git_mcp/gemini_commands/__init__.py
git_mcp/gemini_commands/doc.toml
git_mcp/gemini_commands/implement.toml
git_mcp/gemini_commands/issue.toml
git_mcp/gemini_commands/plan.toml
git_mcp/gemini_commands/pr.toml
git_mcp/gemini_commands/test.toml
git_mcp/platforms/__init__.py
git_mcp/platforms/base.py
git_mcp/platforms/github.py
git_mcp/platforms/gitlab.py
git_mcp/services/__init__.py
git_mcp/services/platform_service.py
git_mcp/utils/__init__.py
git_mcp/utils/output.py
git_mcp/utils/platform.py
git_mcp_server-0.2.4.dist-info/METADATA
git_mcp_server-0.2.4.dist-info/WHEEL
git_mcp_server-0.2.4.dist-info/entry_points.txt
git_mcp_server-0.2.4.dist-info/RECORD
