Metadata-Version: 2.4
Name: git_mcp_server
Version: 0.2.4
Summary: Git MCP Server - Unified command-line tool for managing Git repositories across GitHub and GitLab
Requires-Python: >=3.13
Requires-Dist: click>=8.1.0
Requires-Dist: gitpython>=3.1.0
Requires-Dist: httpx>=0.26.0
Requires-Dist: keyring>=24.0.0
Requires-Dist: mcp[cli]>=1.0.0
Requires-Dist: pre-commit>=4.2.0
Requires-Dist: pydantic>=2.5.0
Requires-Dist: pygithub>=2.1.0
Requires-Dist: python-gitlab>=4.4.0
Requires-Dist: pyyaml>=6.0.0
Requires-Dist: rich>=13.0.0
Requires-Dist: tomli-w>=1.0.0
Requires-Dist: tomli>=2.0.0; python_version < '3.11'
Requires-Dist: tool>=0.8.0
Provides-Extra: dev
Requires-Dist: bandit[toml]>=1.7.0; extra == 'dev'
Requires-Dist: coverage>=7.0.0; extra == 'dev'
Requires-Dist: pip-audit>=2.0.0; extra == 'dev'
Requires-Dist: pre-commit>=4.2.0; extra == 'dev'
Requires-Dist: pytest-asyncio>=0.23.0; extra == 'dev'
Requires-Dist: pytest-cov>=5.0.0; extra == 'dev'
Requires-Dist: pytest>=8.0.0; extra == 'dev'
Requires-Dist: ruff>=0.1.0; extra == 'dev'
